{
  "name": "auth",
  "runtime": "nodejs4.3",
  "description": "Serverless Lambda function for project: keboola-developer-portal",
  "customName": false,
  "customRole": false,
  "handler": "auth/handler.handler",
  "timeout": 10,
  "memorySize": 128,
  "authorizer": {},
  "custom": {
    "excludePatterns": []
  },
  "endpoints": [
    {
      "path": "auth/login",
      "method": "POST",
      "type": "AWS",
      "authorizationType": "none",
      "authorizerFunction": false,
      "apiKeyRequired": false,
      "requestParameters": {},
      "requestTemplates": {
        "application/json": ""
      },
      "responses": {
        "400": {
          "statusCode": "400"
        },
        "default": {
          "statusCode": "200",
          "responseParameters": {},
          "responseModels": {
            "application/json;charset=UTF-8": "Empty"
          },
          "responseTemplates": {
            "application/json;charset=UTF-8": ""
          }
        }
      }
    },
    {
      "path": "auth/signup",
      "method": "POST",
      "type": "AWS",
      "authorizationType": "none",
      "authorizerFunction": false,
      "apiKeyRequired": false,
      "requestParameters": {},
      "requestTemplates": {
        "application/json": ""
      },
      "responses": {
        "400": {
          "statusCode": "400"
        },
        "default": {
          "statusCode": "200",
          "responseParameters": {},
          "responseModels": {
            "application/json;charset=UTF-8": "Empty"
          },
          "responseTemplates": {
            "application/json;charset=UTF-8": ""
          }
        }
      }
    }
  ],
  "events": [],
  "environment": {
    "SERVERLESS_PROJECT": "${project}",
    "SERVERLESS_STAGE": "${stage}",
    "SERVERLESS_REGION": "${region}",
      "COGNITO_IDENTITY_POOL_ID": "${cognitoIdentityPoolId}",
      "COGNITO_DEVELOPER_PROVIDER_NAME": "${cognitoDeveloperProviderName}",
      "TOKEN_SECRET": "${jwtTokenSecret}"
  },
  "vpc": {
    "securityGroupIds": [],
    "subnetIds": []
  }
}